likes/__init__.py
likes/admin.py
likes/apps.py
likes/models.py
likes/selectors.py
likes/services.py
likes/settings.py
likes/signals.py
likes/utils.py
likes/api/__init__.py
likes/api/fields.py
likes/api/pagination.py
likes/api/serializers.py
likes/api/urls.py
likes/api/views.py
likes/locale/en/LC_MESSAGES/django.po
likes/locale/ru/LC_MESSAGES/django.po
likes/locale/uk/LC_MESSAGES/django.po
likes/migrations/0001_initial.py
likes/migrations/__init__.py
likes/templatetags/__init__.py
likes/templatetags/jinja_ok_likes.py
likes/templatetags/ok_likes.py
likes/tests/__init__.py
likes/tests/settings.py
likes/tests/test_api_views.py
likes/tests/test_models.py
likes/tests/test_tags.py
likes/tests/urls.py
django_ok_likes-0.7.4.dist-info/LICENSE
django_ok_likes-0.7.4.dist-info/METADATA
django_ok_likes-0.7.4.dist-info/WHEEL
django_ok_likes-0.7.4.dist-info/top_level.txt
django_ok_likes-0.7.4.dist-info/RECORD
