Metadata-Version: 2.1
Name: django-ok-likes
Version: 0.7.4
Summary: Django likes app
Home-page: https://github.com/LowerDeez/ok-likes
Author: Oleg Kleschunov
Author-email: igorkleschunov@gmail.com
License: MIT
Keywords: python,likes,likes-models,django,voting
Platform: UNKNOWN
Classifier: Environment :: Web Environment
Classifier: Development Status :: 4 - Beta
Classifier: Operating System :: OS Independent
Classifier: Framework :: Django :: 2.0
Classifier: Framework :: Django :: 2.1
Classifier: Intended Audience :: Developers
Classifier: Programming Language :: Python :: 3.6
Classifier: Programming Language :: Python :: 3.7
Requires-Dist: djangorestframework
